{
  "type": "Feature",
  "properties": {
    "@id": "way/51284660",
    "highway": "residential",
    "maxspeed": "RO:urban"
  },
  "geometry": {
    "type": "LineString",
    "coordinates": [
      [
        23.5358784,
        46.7855484
      ],
      [
        23.53484,
        46.78439
      ],
      [
        23.53467,
        46.78427
      ],
      [
        23.53434,
        46.78415
      ],
      [
        23.53411,
        46.78399
      ],
      [
        23.53349,
        46.78338
      ],
      [
        23.53356,
        46.78324
      ],
      [
        23.53408,
        46.78295
      ],
      [
        23.53413,
        46.78282
      ],
      [
        23.5341283,
        46.782756
      ],
      [
        23.5340763,
        46.7827033
      ],
      [
        23.5340427,
        46.7826765
      ],
      [
        23.5340179,
        46.7826525
      ],
      [
        23.533885,
        46.7825455
      ],
      [
        23.5318,
        46.78362
      ],
      [
        23.5317092,
        46.7836801
      ],
      [
        23.53118,
        46.78403
      ],
      [
        23.53068,
        46.78423
      ],
      [
        23.52964,
        46.78454
      ],
      [
        23.52938,
        46.78457
      ],
      [
        23.52917,
        46.78445
      ],
      [
        23.52843,
        46.78385
      ],
      [
        23.52786,
        46.78328
      ],
      [
        23.52771,
        46.78304
      ],
      [
        23.5272777,
        46.782546
      ],
      [
        23.52694,
        46.78216
      ],
      [
        23.52655,
        46.78149
      ],
      [
        23.52633,
        46.7814
      ],
      [
        23.52551,
        46.78126
      ],
      [
        23.52452,
        46.78096
      ],
      [
        23.52397,
        46.78063
      ],
      [
        23.52216,
        46.78003
      ],
      [
        23.52179,
        46.77985
      ],
      [
        23.52141,
        46.7794
      ],
      [
        23.5213274,
        46.7793359
      ]
    ]
  },
  "id": "way/51284660"
}