{
  "type": "Feature",
  "properties": {
    "@id": "way/61185664",
    "highway": "pedestrian",
    "is_in:city": "Cluj-Napoca"
  },
  "geometry": {
    "type": "LineString",
    "coordinates": [
      [
        23.6155188,
        46.7599949
      ],
      [
        23.6154977,
        46.760137
      ],
      [
        23.615425,
        46.7605001
      ],
      [
        23.615426,
        46.7606769
      ],
      [
        23.6153847,
        46.7607812
      ],
      [
        23.6154115,
        46.760907
      ]
    ]
  },
  "id": "way/61185664"
}