{
  "type": "Feature",
  "properties": {
    "@id": "way/144459355",
    "highway": "primary",
    "int_ref": "E60",
    "is_in:city": "Cluj-Napoca",
    "junction": "roundabout",
    "maxspeed": "RO:urban",
    "name": "Calea Turzii",
    "name:hu": "Tordai út"
  },
  "geometry": {
    "type": "LineString",
    "coordinates": [
      [
        23.5960652,
        46.7558069
      ],
      [
        23.5960961,
        46.755773
      ],
      [
        23.5961466,
        46.7557468
      ],
      [
        23.5962245,
        46.7557349
      ],
      [
        23.5962959,
        46.7557469
      ],
      [
        23.596347,
        46.7557737
      ],
      [
        23.596378,
        46.7558086
      ],
      [
        23.5963892,
        46.7558485
      ],
      [
        23.5963781,
        46.7558913
      ],
      [
        23.5963583,
        46.7559167
      ],
      [
        23.5963051,
        46.7559498
      ],
      [
        23.5962502,
        46.7559635
      ],
      [
        23.5962112,
        46.7559651
      ],
      [
        23.5961455,
        46.755953
      ],
      [
        23.5961001,
        46.7559301
      ],
      [
        23.5960604,
        46.755884
      ],
      [
        23.5960547,
        46.7558334
      ],
      [
        23.5960652,
        46.7558069
      ]
    ]
  },
  "id": "way/144459355"
}