{
  "type": "Feature",
  "properties": {
    "@id": "way/44606997",
    "highway": "primary",
    "int_ref": "E 60;E 81",
    "is_in:city": "Cluj-Napoca",
    "lanes": "4",
    "maxspeed": "50",
    "name": "Calea Turzii",
    "name:hu": "Tordai út",
    "ref": "DN1"
  },
  "geometry": {
    "type": "LineString",
    "coordinates": [
      [
        23.5928664,
        46.7469993
      ],
      [
        23.5929736,
        46.7474931
      ],
      [
        23.5931297,
        46.7479727
      ],
      [
        23.5931842,
        46.748078
      ],
      [
        23.5933011,
        46.7483037
      ],
      [
        23.5939325,
        46.7496253
      ],
      [
        23.5941583,
        46.7500754
      ],
      [
        23.5942084,
        46.750181
      ],
      [
        23.5944021,
        46.7505893
      ],
      [
        23.5947739,
        46.7512706
      ],
      [
        23.5950855,
        46.7518415
      ],
      [
        23.59568,
        46.7530538
      ],
      [
        23.5958402,
        46.7533655
      ],
      [
        23.5959192,
        46.7538377
      ],
      [
        23.5959951,
        46.7541875
      ],
      [
        23.5960529,
        46.7544195
      ],
      [
        23.596086,
        46.7545659
      ],
      [
        23.5961481,
        46.7547745
      ]
    ]
  },
  "id": "way/44606997"
}