{
  "type": "Feature",
  "properties": {
    "@id": "way/118146070",
    "highway": "residential",
    "maxspeed": "RO:urban",
    "name": "Strada Școlii",
    "name:hu": "Iskola utca"
  },
  "geometry": {
    "type": "LineString",
    "coordinates": [
      [
        23.5535498,
        46.7813049
      ],
      [
        23.5535125,
        46.7817796
      ],
      [
        23.5534943,
        46.782011
      ],
      [
        23.5535498,
        46.7823803
      ],
      [
        23.5536431,
        46.7824743
      ],
      [
        23.5536847,
        46.7825161
      ],
      [
        23.5538592,
        46.7826084
      ],
      [
        23.5540575,
        46.7826627
      ],
      [
        23.5542557,
        46.7826844
      ],
      [
        23.5546206,
        46.7826953
      ],
      [
        23.5559927,
        46.7826193
      ],
      [
        23.5562941,
        46.7826573
      ],
      [
        23.5564528,
        46.7827116
      ],
      [
        23.5565162,
        46.7827496
      ],
      [
        23.556778,
        46.7829832
      ],
      [
        23.557,
        46.7831624
      ],
      [
        23.5576146,
        46.7835591
      ]
    ]
  },
  "id": "way/118146070"
}