{
  "type": "Feature",
  "properties": {
    "@id": "way/31619664",
    "highway": "residential",
    "is_in:city": "Cluj-Napoca",
    "junction": "roundabout",
    "maxspeed": "RO:urban",
    "name": "Strada Arinilor",
    "name:hu": "Éger utca",
    "old_name:hu": "Bölöni Farkas Sándor utca"
  },
  "geometry": {
    "type": "LineString",
    "coordinates": [
      [
        23.5473567,
        46.7596355
      ],
      [
        23.5474125,
        46.7596509
      ],
      [
        23.5474508,
        46.7596733
      ],
      [
        23.547482,
        46.7597085
      ],
      [
        23.547491,
        46.7597306
      ],
      [
        23.5474867,
        46.759785
      ],
      [
        23.5474504,
        46.75983
      ],
      [
        23.5474034,
        46.7598557
      ],
      [
        23.5473691,
        46.7598654
      ],
      [
        23.5473093,
        46.7598699
      ],
      [
        23.5472754,
        46.7598661
      ],
      [
        23.5472056,
        46.7598403
      ],
      [
        23.5471682,
        46.7598081
      ],
      [
        23.5471519,
        46.7597787
      ],
      [
        23.5471478,
        46.7597419
      ],
      [
        23.5471634,
        46.7597014
      ],
      [
        23.5471979,
        46.7596676
      ],
      [
        23.5472557,
        46.7596414
      ],
      [
        23.5473146,
        46.7596329
      ],
      [
        23.5473567,
        46.7596355
      ]
    ]
  },
  "id": "way/31619664"
}