{
  "type": "Feature",
  "properties": {
    "@id": "way/31586019",
    "highway": "residential",
    "is_in:city": "Cluj-Napoca",
    "maxspeed": "RO:urban",
    "name": "Strada Bobâlna"
  },
  "geometry": {
    "type": "LineString",
    "coordinates": [
      [
        23.6266525,
        46.7909321
      ],
      [
        23.6261633,
        46.7904855
      ],
      [
        23.6261032,
        46.7904267
      ],
      [
        23.6260603,
        46.7903092
      ],
      [
        23.6259831,
        46.7902563
      ],
      [
        23.6258715,
        46.7902152
      ],
      [
        23.6227644,
        46.789222
      ],
      [
        23.6209191,
        46.7886696
      ],
      [
        23.620262,
        46.7885207
      ],
      [
        23.6197003,
        46.7883934
      ],
      [
        23.619623,
        46.78827
      ]
    ]
  },
  "id": "way/31586019"
}