{
  "type": "Feature",
  "properties": {
    "@id": "way/239189344",
    "highway": "residential",
    "is_in:city": "Cluj-Napoca",
    "maxspeed": "50",
    "name": "Strada Donath"
  },
  "geometry": {
    "type": "LineString",
    "coordinates": [
      [
        23.5571444,
        46.7721933
      ],
      [
        23.5560951,
        46.7719942
      ],
      [
        23.5559633,
        46.771968
      ],
      [
        23.555664,
        46.7719084
      ],
      [
        23.5551054,
        46.7717842
      ],
      [
        23.5543565,
        46.7716176
      ],
      [
        23.5537887,
        46.7714935
      ],
      [
        23.5532999,
        46.7713867
      ],
      [
        23.5528936,
        46.7713077
      ],
      [
        23.5527197,
        46.7712558
      ],
      [
        23.5525578,
        46.7711924
      ],
      [
        23.5516649,
        46.7707579
      ],
      [
        23.5508116,
        46.7703427
      ],
      [
        23.5501828,
        46.7700215
      ],
      [
        23.5488511,
        46.7692332
      ],
      [
        23.5486659,
        46.7691352
      ],
      [
        23.5485987,
        46.7690144
      ],
      [
        23.5485937,
        46.7688785
      ],
      [
        23.5487389,
        46.7685735
      ],
      [
        23.5487422,
        46.7684149
      ]
    ]
  },
  "id": "way/239189344"
}